pyMensa/Mensa.py
pyMensa/__init__.py
pyMensa-1.0.1.dist-info/LICENSE
pyMensa-1.0.1.dist-info/METADATA
pyMensa-1.0.1.dist-info/WHEEL
pyMensa-1.0.1.dist-info/top_level.txt
pyMensa-1.0.1.dist-info/RECORD
