Metadata-Version: 2.1
Name: pyMensa
Version: 1.0.1
Summary: A python package for fetching mensa menus at ETH and UNI Zürich
Home-page: https://github.com/pasch13/pyMensa
Author: Pascal Schärli
Author-email: pas.schaerli@sunrise.ch
License: UNKNOWN
Platform: UNKNOWN
Classifier: Programming Language :: Python :: 3
Classifier: License :: OSI Approved :: MIT License
Classifier: Operating System :: OS Independent
